dophon_mq/__init__.py
dophon_mq/bone_data.py
dophon_mq/function_unit/__init__.py
dophon_mq/function_unit/Consumer.py
dophon_mq/function_unit/Producer.py
dophon_mq/function_unit/SizeableTPE.py
dophon_mq/local/__init__.py
dophon_mq/local/MsgCenter.py
dophon_mq/properties/__init__.py
dophon_mq/properties/default_properties.py
dophon_mq/properties/properties.py
dophon_mq/remote/__init__.py
dophon_mq/remote/remote_center.py
dophon_mq/utils.py
dophon_mq-1.0.0.post5.dist-info/LICENSE
dophon_mq-1.0.0.post5.dist-info/WHEEL
dophon_mq-1.0.0.post5.dist-info/METADATA
dophon_mq-1.0.0.post5.dist-info/RECORD
