Metadata-Version: 2.1
Name: dophon-mq
Version: 1.0.0.post5
Summary: dophon mq module
Home-page: UNKNOWN
License: UNKNOWN
Author: CallMeE
Author-email: ealohu@163.com
Requires-Python: >=3.6,<4.0
Classifier: Programming Language :: Python :: 3
Classifier: Programming Language :: Python :: 3.6
Classifier: Programming Language :: Python :: 3.7
